[
    {
        "name": "Fredrik Söderqvist",
        "image": "fredrik.jpg",
        "description": "Ordförande, uppgång J",
        "mail1": "fredrik (punkt) soderqvist (at) omberg3 (punkt) se",
        "mail2": "",
        "phone": "0706-690897"
    },
    {
        "name": "David Elmqvist",
        "image": "david.jpg",
        "description": "Uppgång E",
        "mail1": "david (punkt) elmqvist (at) gmail (punkt) com",
        "mail2": "david (punkt) elmqvist (at) omberg3 (punkt) se",
        "phone": "073-3266134"
    },
    {
        "name": "Mikael Skoog",
        "image": "",
        "description": "Uppgång N",
        "mail1": "mikael (at) gelnet (punkt) se",
        "mail2": "",
        "phone": "070-8296952"
    },
    {
        "name": "Lisa Albinsson Fimreite",
        "image": "",
        "description": "Uppgång K",
        "mail1": "Lisa (punkt) Fimreite (at) telia (punkt) com",
        "mail2": "",
        "phone": ""
    },
    {
        "name": "Sofia Rosendahl",
        "image": "",
        "description": "Uppgång J",
        "mail1": "sofiarosendahl (at) hotmail (punkt) com",
        "mail2": "",
        "phone": ""
    },
    {
        "name": "Lennart Falk",
        "image": "lennart_falk.jpg",
        "description": "Representant HSB",
        "mail1": "lennart (punkt) falk (at) gbg (punkt) hsb (punkt) se",
        "mail2": "",
        "phone": ""
    }
]

